{
	"TutorialInventory": {
		"EventCategory": "TUTORIAL",
		"EventPrerequisiteFlags": [],
		"EventCompletionFlags": [
			"TutorialInventory_Done"
		],
		"Oneshot": true,
		"EventText": {
			"Name": "Tutorial",
			"Text": {
				"Press the 'X' Button on the Left Controller.": 3,
				"This Opens the Inventory System": 3,
				"Pressing the 'X' Button again closes the Inventory": 3
			}
		},
		"EventLocations": [
			"Mansion Entrance"
		],
		"DialogueClickable": true
	},
	"ActionPickUpJournal": {
		"EventCategory": "ACTION",
		"EventPrerequisiteFlags": [],
		"EventCompletionFlags": [
			"ActionPickUpJournal_Done"
		],
		"Oneshot": true,
		"EventText": {

		},
		"EventLocations": [
			"Mansion Entrance"
		],
		"DialogueClickable": false
	},
	"TutorialJournalQuestLog": {
		"EventCategory": "TUTORIAL",
		"EventPrerequisiteFlags": [
			"ActionPickUpJournal_Done"
		],
		"EventCompletionFlags": [
			"TutorialJournalQuestLog_Done"
		],
		"Oneshot": true,
		"EventText": {
			"Name": "Tutorial",
			"Text": {
				"This is your Journal": 2,
				"This is the Task List Section of the Journal": 3,
				"This section contains information about the current task you need to accomplish": 4,
				"Make sure to check your Journal often to see updates about your task progress": 4
			}
		},
		"EventLocations": [
			"Mansion Entrance"
		],
		"DialogueClickable": true
	},
	"ActionPickUpFlashlight": {
		"EventCategory": "ACTION",
		"EventPrerequisiteFlags": [],
		"EventCompletionFlags": [
			"ActionPickUpFlashlight_Done"
		],
		"Oneshot": true,
		"EventText": {

		},
		"EventLocations": [
			"Mansion Entrance"
		],
		"DialogueClickable": false
	},
	"TutorialFlashlightRadio": {
		"EventCategory": "TUTORIAL",
		"EventPrerequisiteFlags": [
			"ActionPickUpFlashlight_Done"
		],
		"EventCompletionFlags": [
			"TutorialFlashlightRadio_Done"
		],
		"Oneshot": true,
		"EventText": {
			"Name": "Tutorial",
			"Text": {
				"This is the Flashlight Radio.": 3,
				"This is useful as a light source when navigating dark areas": 4,
				"You can also grab on to the crank.": 3,
				"Cranking the flashlight 3 times will give you a hint about how to progress": 4,
				"Give it a go!": 2
			}
		},
		"EventLocations": [
			"Mansion Entrance"
		],
		"DialogueClickable": true
	},
	"TutorialTeleport": {
		"EventCategory": "TUTORIAL",
		"EventPrerequisiteFlags": [
			"ActionShineLightOnTele_Done"
		],
		"EventCompletionFlags": [
			"TutorialTeleport_Done",
			"TeleportSofasActivate"
		],
		"Oneshot": true,
		"EventText": {
			"Name": "Tutorial",
			"Text": {
				"The circles on the ground are movement points.": 4,
				"Pointing at them and pressing the trigger will move you to the location of the circle": 4,
				"White Circles are movement points you can access at your current location.": 4,
				"Blue Circles are movement points are inaccessible for a variety of reasons, whether it be task requirements or distance": 5
			}
		},
		"EventLocations": [
			"Mansion Entrance"
		],
		"DialogueClickable": true
	},
	"ActionTeleportToSofas": {
		"EventCategory": "ACTION",
		"EventPrerequisiteFlags": [
			"TutorialTeleport_Done"
		],
		"EventCompletionFlags": [
			"ActionTeleportToSofas_Done"
		],
		"Oneshot": true,
		"EventText": {

		},
		"EventLocations": [],
		"DialogueClickable": false
	},
	"ActionShineLightOnTele": {
		"EventCategory": "ACTION",
		"EventPrerequisiteFlags": [
			"TutorialFlashlightRadio_Done"
		],
		"EventCompletionFlags": [
			"ActionShineLightOnTele_Done"
		],
		"Oneshot": true,
		"EventText": {

		},
		"EventLocations": [
			"Mansion Entrance"
		],
		"DialogueClickable": false
	}
}
